README.rst
setup.py
setupext/__init__.py
setupext.egg-info/PKG-INFO
setupext.egg-info/SOURCES.txt
setupext.egg-info/dependency_links.txt
setupext.egg-info/not-zip-safe
setupext.egg-info/top_level.txt
setupext/doc/LICENSE-GPLv3.txt
setupext/doc/README.md
setupext/doc/README.rst
setupext/doc/setup-sample.py