Metadata-Version: 1.1
Name: setupext
Version: 0.24.8
Summary: Utility classes and methods for using setuptools
Home-page: https://github.com/sundarnagarajan/setupext
Author: Sundar Nagarajan
Author-email: sun.nagarajan@gmail.com
License: License :: OSI Approved :: GNU Lesser General Public License v3 or later (LGPLv3+)
Download-URL: https://github.com/sundarnagarajan/setupext.git
Platform: UNKNOWN
Classifier: Development Status :: 4 - Beta
Classifier: Programming Language :: Python :: 2
Classifier: Programming Language :: Python :: 3
Classifier: Programming Language :: Python :: Implementation :: PyPy
Classifier: License :: OSI Approved :: GNU Lesser General Public License v3 or later (LGPLv3+)
